zz_tool/__init__.py
zz_tool/cli.py
utils_1z-0.1.dist-info/METADATA
utils_1z-0.1.dist-info/WHEEL
utils_1z-0.1.dist-info/entry_points.txt
utils_1z-0.1.dist-info/top_level.txt
utils_1z-0.1.dist-info/RECORD
