Metadata-Version: 2.4
Name: utils-1z
Version: 0.1
Summary: Utility CLI tool
Author: ubuntu
Requires-Python: >=3.6
Dynamic: author
Dynamic: requires-python
Dynamic: summary
